{"name": "*爱看影院",
"tihuan": "cnzz.com",
"url": "https://www.readav.com",
"fenlei": "国产视频$/index.php/vod/type/id/1/page/#日本视频$/index.php/vod/type/id/2/page/#VR视频$/index.php/vod/type/id/3/page/#韩国视频$/index.php/vod/type/id/4/page/#欧美视频$/index.php/vod/type/id/5/page/#动画视频$/index.php/vod/type/id/6/page/6#中文字幕$/index.php/vod/type/id/9/page/#国产精品$/index.php/vod/show/id/10/page/#精品三级$/index.php/vod/show/id/11/page/#主播大秀$/index.php/vod/show/id/12/page/#抖阴视频$/index.php/vod/show/id/13/page/#国模私拍$/index.php/vod/show/id/14/page/#颜射瞬间$/index.php/vod/show/id/15/page/#女神学生$/index.php/vod/show/id/16/page/#美熟少妇$/index.php/vod/show/id/17/page/#娇妻素人$/index.php/vod/show/id/18/page/#空姐模特$/index.php/vod/show/id/19/page/#国产乱伦$/index.php/vod/show/id/20/page/#骑兵有码$/index.php/vod/show/id/27/page/#步兵无码$/index.php/vod/show/id/28/page/#制服师生$/index.php/vod/show/id/50/page/#强奸乱伦$/index.php/vod/show/id/51/page/#人妻熟女$/index.php/vod/show/id/53/page/#三级剧情$/index.php/vod/show/id/55/page/#丝袜美腿$/index.php/vod/show/id/56/page/#亚洲情色$/index.php/vod/show/id/58/page/#VR有码$/index.php/vod/show/id/7/page/#VR无码$/index.php/vod/show/id/8/page/#韩国精品$/index.php/vod/show/id/42/page/#韩国制服主播$/index.php/vod/show/id/43/page/#韩国萝莉主播$/index.php/vod/show/id/44/page/#韩国大秀主播$/index.php/vod/show/id/45/page/#韩国自慰主播$/index.php/vod/show/id/46/page/#韩国唯美三级$/index.php/vod/show/id/47/page/#韩国明星学生$/index.php/vod/show/id/48/page/#无码中文$/index.php/vod/show/id/34/page/#强奸中文$/index.php/vod/show/id/35/page/#巨乳中文$/index.php/vod/show/id/36/page/#乱伦中文$/index.php/vod/show/id/37/page/#制服中文$/index.php/vod/show/id/38/page/#人妻中文$/index.php/vod/show/id/39/page/#调教中文$/index.php/vod/show/id/40/page/#出轨中文$/index.php/vod/show/id/41/page/#中文字幕$/index.php/vod/show/id/59/page/#卡通动漫$/index.php/vod/show/id/49/page/#欧美性爱$/index.php/vod/show/id/29/page/#欧美人兽$/index.php/vod/show/id30/page/#欧美人妖$/index.php/vod/show/id/31/page/#欧美男同$/index.php/vod/show/id/32/page/#欧美女同$/index.php/vod/show/id/33/page/",
"houzhui": ".html",
"shifouercijiequ": "0",
"jiequqian": "空",
"jiequhou": "空",
"jiequshuzuqian":"class=\"stui-vodlist",
"jiequshuzuhou": "</h4>",
"tupianqian":"data-original=\"",
"tupianhou": "\"",
"biaotiqian": "title=\"",
"biaotihou": "\"",
"lianjieqian": "href=\"",
"lianjiehou": "\"",
"sousuoqian": "/index.php/ajax/suggest?mid=1&wd=",
"sousuohou": "&limit=500",
"sousuohouzhui": "/detail/",
"ssmoshi": "0",
"sousuoshifouercijiequ": "0",
"jspic": "pic",
"jsname": "name",
"jsid": "id",
"ssjiequqian": "空",
"ssjiequhou": "空",
"ssjiequshuzuqian": "空",
"ssjiequshuzuhou": "空",
"sstupianqian": "空",
"sstupianhou": "空",
"ssbiaotiqian": "空",
"ssbiaotihou": "空",
"sslianjieqian": "空",
"sslianjiehou": "空",
"bfshifouercijiequ": "0",
"bfjiequqian": "空",
"bfjiequhou": "空",
"bfjiequshuzuqian": "class=\"stui-content__playlist",
"bfjiequshuzuhou": "</ul>",
"zhuangtaiqian": "class=\"text-muted hidden-xs\">类型：",
"zhuangtaihou": "</a>",
"daoyanqian": "class=\"data\">导演：",
"daoyanhou": "</p>",
"zhuyanqian": "class=\"data\">主演：",
"zhuyanhou": "</p>",
"juqingqian": "class=\"detail-content\"",
"juqinghou": "</span>",
"bfyshifouercijiequ": "0",
"bfyjiequqian": "空",
"bfyjiequhou": "空",
"bfyjiequshuzuqian": "<a",
"bfyjiequshuzuhou": "/a>",
"bfbiaotiqian": ">",
"bfbiaotihou": "<",
"bflianjieqian": "href=\"",
"bflianjiehou": "\""}